hestia_earth/flowmaps/__init__.py
hestia_earth/flowmaps/version.py
hestia_earth/flowmaps/RosettaFlow/__init__.py
hestia_earth/flowmaps/RosettaFlow/file_shemas.py
hestia_earth/flowmaps/RosettaFlow/file_validation.py
hestia_earth_flowmaps-0.1.4.dist-info/licenses/LICENSE
hestia_earth_flowmaps-0.1.4.dist-info/METADATA
hestia_earth_flowmaps-0.1.4.dist-info/WHEEL
hestia_earth_flowmaps-0.1.4.dist-info/top_level.txt
hestia_earth_flowmaps-0.1.4.dist-info/RECORD
