Metadata-Version: 2.4
Name: hestia_earth_flowmaps
Version: 0.1.4
Summary: HESTIA's flowmaps for converters
Home-page: https://gitlab.com/hestia-earth/hestia-convert-flowmaps
Author: HESTIA Team
Author-email: guillaumeroyer.mail@gmail.com
License: MIT
Classifier: Programming Language :: Python :: 3.12
Requires-Python: >=3.12
License-File: LICENSE
Requires-Dist: hestia-earth-utils>=0.16.7
Requires-Dist: pydantic==2.*
Requires-Dist: pydantic_core==2.*
Requires-Dist: python-dateutil
Requires-Dist: numpy
Requires-Dist: pandas
Dynamic: author
Dynamic: author-email
Dynamic: classifier
Dynamic: description
Dynamic: description-content-type
Dynamic: home-page
Dynamic: license
Dynamic: license-file
Dynamic: requires-dist
Dynamic: requires-python
Dynamic: summary
